{"schema":6,"addons":[{"id":"langpack-en-GB@firefox.mozilla.org","icons":{"32":"https://addons.cdn.mozilla.net/static/img/addon-icons/default-32.png?v=20210601","64":"https://addons.cdn.mozilla.net/static/img/addon-icons/default-64.png?v=20210601","128":"https://addons.cdn.mozilla.net/static/img/addon-icons/default-128.png?v=20210601"},"name":"English (GB) Language Pack","version":"92.0buildid20210824191834","sourceURI":"https://addons.mozilla.org/firefox/downloads/file/3830033/english_gb_language_pack-92.0buildid20210824191834-fx.xpi","homepageURL":null,"supportURL":null,"description":"English (GB) Language Pack","fullDescription":null,"weeklyDownloads":1577,"type":"locale","creator":{"name":"Mozilla Firefox","url":"https://addons.mozilla.org/en-US/firefox/user/4757633/"},"developers":[],"screenshots":[],"contributionURL":"","averageRating":3.6752,"reviewCount":220,"reviewURL":"https://addons.mozilla.org/en-US/firefox/addon/english-gb-language-pack/reviews/","updateDate":1629840386000},{"id":"langpack-en-CA@firefox.mozilla.org","icons":{"32":"https://addons.cdn.mozilla.net/static/img/addon-icons/default-32.png?v=20210601","64":"https://addons.cdn.mozilla.net/static/img/addon-icons/default-64.png?v=20210601","128":"https://addons.cdn.mozilla.net/static/img/addon-icons/default-128.png?v=20210601"},"name":"English (CA) Language Pack","version":"92.0buildid20210824191834","sourceURI":"https://addons.mozilla.org/firefox/downloads/file/3830030/english_ca_language_pack-92.0buildid20210824191834-fx.xpi","homepageURL":null,"supportURL":null,"description":"Language pack for Firefox for en-CA","fullDescription":null,"weeklyDownloads":111,"type":"locale","creator":{"name":"Mozilla Firefox","url":"https://addons.mozilla.org/en-US/firefox/user/4757633/"},"developers":[],"screenshots":[],"contributionURL":"","averageRating":4.3243,"reviewCount":4,"reviewURL":"https://addons.mozilla.org/en-US/firefox/addon/english-ca-language-pack/reviews/","updateDate":1629840383000}]}